LICENSE
MANIFEST.in
README.md
setup.py
coronacheck_tools/__init__.py
coronacheck_tools/cli.py
coronacheck_tools.egg-info/PKG-INFO
coronacheck_tools.egg-info/SOURCES.txt
coronacheck_tools.egg-info/dependency_links.txt
coronacheck_tools.egg-info/entry_points.txt
coronacheck_tools.egg-info/requires.txt
coronacheck_tools.egg-info/top_level.txt
coronacheck_tools/api/__init__.py
coronacheck_tools/api/decoder.py
coronacheck_tools/api/denylist.py
coronacheck_tools/api/encoder.py
coronacheck_tools/certificate_versions/__init__.py
coronacheck_tools/certificate_versions/v2.py
coronacheck_tools/clitools/__init__.py
coronacheck_tools/clitools/convert.py
coronacheck_tools/clitools/definitions.py
coronacheck_tools/clitools/iotool.py
coronacheck_tools/common/__init__.py
coronacheck_tools/common/conversion.py
coronacheck_tools/common/qrtools.py
coronacheck_tools/lib/__init__.py
coronacheck_tools/lib/verifier-darwin-amd64.so
coronacheck_tools/lib/verifier-linux-386.so
coronacheck_tools/lib/verifier-linux-amd64.so
coronacheck_tools/lib/verifier-linux-arm64.so
coronacheck_tools/lib/verifier-linux-armv5.so
coronacheck_tools/lib/verifier-linux-armv6.so
coronacheck_tools/lib/verifier-linux-armv6l.so
coronacheck_tools/lib/verifier-linux-armv7.so
coronacheck_tools/lib/verifier-linux-ppc64le.so
coronacheck_tools/lib/verifier-windows-386.dll
coronacheck_tools/lib/verifier-windows-amd64.dll
coronacheck_tools/verification/__init__.py
coronacheck_tools/verification/mobilecore.py
coronacheck_tools/verification/verifier.py
test/__init__.py
test/common.py
test/generate_test_data.py
test/test_cli.py
test/test_config.py
test/test_decode.py
test/test_encode.py
test/test_validate.py