Metadata-Version: 2.1
Name: coronacheck-tools
Version: 3
Summary: Unofficial tool to encode, decode and verify the QR code from CoronaCheck.nl. Not affiliated with CoronaCheck.nl or Ministry of VWS.
Home-page: https://github.com/Sikerdebaard/coronacheck-tools
Author: Thomas Phil
Author-email: thomas@tphil.nl
License: UNKNOWN
Platform: UNKNOWN
Requires-Python: >=3.6
License-File: LICENSE
